athemala.py
setup.py
athemala.egg-info/PKG-INFO
athemala.egg-info/SOURCES.txt
athemala.egg-info/dependency_links.txt
athemala.egg-info/top_level.txt