Metadata-Version: 1.0
Name: athemala
Version: 0.1.0
Summary: A HTML generation system
Home-page: https://github.com/siemer/athemala
Author: Robert Siemer
Author-email: Robert.Siemer-pypi@backsla.sh
License: AGPL3
Platform: UNKNOWN
